rapidinstall/__init__.py
rapidinstall/pip_concurrent.py
rapidinstall/run.py
rapidinstall-1.2.2.dist-info/licenses/LICENSE
rapidinstall-1.2.2.dist-info/METADATA
rapidinstall-1.2.2.dist-info/WHEEL
rapidinstall-1.2.2.dist-info/entry_points.txt
rapidinstall-1.2.2.dist-info/top_level.txt
rapidinstall-1.2.2.dist-info/RECORD
