Metadata-Version: 2.4
Name: rapidinstall
Version: 1.2.2
Summary: Downloads, Installs in paralell - A utility to run multiple shell command sequences (e.g., installations) in parallel with status updates.
Author-email: Tom <chief-scouter0f@icloud.com>
License-Expression: GPL-3.0-or-later
Project-URL: Homepage, https://github.com/tomOfBerlin/rapidinstall
Project-URL: Bug Tracker, https://github.com/tomOfBerlin/rapidinstall/issues
Keywords: setup,parallel,subprocess,install,shell,script,automation,concurrent,colab
Classifier: Development Status :: 4 - Beta
Classifier: Intended Audience :: Developers
Classifier: Intended Audience :: System Administrators
Classifier: Operating System :: OS Independent
Classifier: Programming Language :: Python :: 3
Classifier: Topic :: Software Development :: Build Tools
Classifier: Topic :: System :: Installation/Setup
Classifier: Topic :: Utilities
Requires-Python: >=3.7
License-File: LICENSE
Provides-Extra: download
Requires-Dist: pySmartDL>=1.3.4; extra == "download"
Provides-Extra: dev
Requires-Dist: pytest; extra == "dev"
Requires-Dist: black; extra == "dev"
Requires-Dist: flake8; extra == "dev"
Dynamic: license-file
